# Ключевое слово volatile
## Смысл `volatile`
Ключевое слово `volatile` обеспечивает видимость изменений в приложении.<br/>
Если поле объявлено с ключевым словом `volatile`, это означает, что сразу же после записи в это поле все операции чтения "увидят" изменение. Это утверждение истино для при использовании локальных кэшей - `volatile`-поля немедленно записываются в основную память, и чтение выполняется из основной памяти.<br/>
_Эккель Б. Философия Java. 4-е полное изд. Стр. 929_

## Атомарность и видимость
Важно понимать, что атомарность и видимость изменений являются разными концепциями.<br/>
Атомарность операции с полем без ключевого слова `volatile` не обязательно будет актуализирована в основной памяти, поэтому другая задача, читающая значение поля, может не увидеть новое значение.<br/>
Если сразу несколько задач обращаются к полю, это поле следует объявить с ключевым словом `volatile`. В противном случае обращения к полю должны осуществляться только через механизмы синхронизации.<br/>
**Синхронизация также вынуждает** запись данных в основную память, и если поле полностю защищено синхронизированными методами или блоками, объявлять его `volatile` не обязательно<br/>
[Пример того, что i++ не атомарна](examples/java/volatile_ex/IsItAtomic.java)
```java
public class IsItAtomic {
    public static void main(String[] args) {
        int i = 0;
        i++;
        System.out.println(i);
    }
}
```
Билдим и выполняем
```
~/IdeaProjects/knowledge_base/java6/build/classes/java/main/ru/akhitev/kb/java6/multithreading/volatile$ javap -c IsItAtomic.class
```
Результат
```
Compiled from "IsItAtomic.java"
public class ru.akhitev.kb.java6.multithreading.volatile.IsItAtomic {
  public ru.akhitev.kb.java6.multithreading.volatile.IsItAtomic();
    Code:
       0: aload_0
       1: invokespecial #1                  // Method java/lang/Object."<init>":()V
       4: return

  public static void main(java.lang.String[]);
    Code:
       0: iconst_0
       1: istore_1
       2: iinc          1, 1
       5: getstatic     #2                  // Field java/lang/System.out:Ljava/io/PrintStream;
       8: iload_1
       9: invokevirtual #3                  // Method java/io/PrintStream.println:(I)V
      12: return
}
```
_Эккель Б. Философия Java. 4-е полное изд. Стр. 929_